kuehn_et_al_fdm/__init__.py
kuehn_et_al_fdm/_common_args.py
kuehn_et_al_fdm/_help.py
kuehn_et_al_fdm/calc_displ_avg.py
kuehn_et_al_fdm/calc_displ_profile.py
kuehn_et_al_fdm/calc_displ_site.py
kuehn_et_al_fdm/calc_params.py
kuehn_et_al_fdm/calc_prob_exceed.py
kuehn_et_al_fdm/calc_prob_occur.py
kuehn_et_al_fdm/load_data.py
kuehn_et_al_fdm/prediction_functions.py
kuehn_et_al_fdm/transformation_functions.py
kuehn_et_al_fdm/utilities.py
kuehn_et_al_fdm/data/coefficients_correlation_NM_powtr.csv
kuehn_et_al_fdm/data/coefficients_correlation_REV_powtr.csv
kuehn_et_al_fdm/data/coefficients_correlation_SS_powtr.csv
kuehn_et_al_fdm/data/coefficients_covariance_NM_powtr.csv
kuehn_et_al_fdm/data/coefficients_covariance_REV_powtr.csv
kuehn_et_al_fdm/data/coefficients_covariance_SS_powtr.csv
kuehn_et_al_fdm/data/coefficients_mean_NM_powtr.csv
kuehn_et_al_fdm/data/coefficients_mean_REV_powtr.csv
kuehn_et_al_fdm/data/coefficients_mean_SS_powtr.csv
kuehn_et_al_fdm/data/coefficients_posterior_NM_powtr.csv
kuehn_et_al_fdm/data/coefficients_posterior_REV_powtr.csv
kuehn_et_al_fdm/data/coefficients_posterior_SS_powtr.csv
kuehn_et_al_fdm/data/uncertainty_NM.csv
kuehn_et_al_fdm/data/uncertainty_REV.csv
kuehn_et_al_fdm/data/uncertainty_SS.csv
kuehn_et_al_fdm-1.0.2.dist-info/AUTHORS.rst
kuehn_et_al_fdm-1.0.2.dist-info/LICENSE
kuehn_et_al_fdm-1.0.2.dist-info/METADATA
kuehn_et_al_fdm-1.0.2.dist-info/WHEEL
kuehn_et_al_fdm-1.0.2.dist-info/entry_points.txt
kuehn_et_al_fdm-1.0.2.dist-info/top_level.txt
kuehn_et_al_fdm-1.0.2.dist-info/RECORD
