Metadata-Version: 2.2
Name: kuehn_et_al_fdm
Version: 1.0.2
Summary: Implementations of the Kuehn et al. 2024 Fault Displacement Model
Author: Alex Sarmiento
License: MIT
Project-URL: homepage, https://github.com/asarmy/kuehn_et_al_fdm
Project-URL: repository, https://github.com/asarmy/kuehn_et_al_fdm
Project-URL: documentation, https://kuehn-et-al-fdm.readthedocs.io/en/latest/index.html
Requires-Python: >=3.7
License-File: LICENSE
License-File: AUTHORS.rst
Requires-Dist: numpy
Requires-Dist: pandas
Requires-Dist: scipy
Provides-Extra: examples
Requires-Dist: jupyter; extra == "examples"
Requires-Dist: matplotlib; extra == "examples"
Requires-Dist: statsmodels; extra == "examples"
Provides-Extra: dev
Requires-Dist: pytest; extra == "dev"
Requires-Dist: pytest-cov; extra == "dev"
Requires-Dist: black; extra == "dev"
Requires-Dist: flake8; extra == "dev"
Requires-Dist: twine; extra == "dev"
Requires-Dist: sphinx; extra == "dev"
Requires-Dist: sphinx_rtd_theme; extra == "dev"
Requires-Dist: sphinxcontrib-bibtex; extra == "dev"
Requires-Dist: pydocstyle; extra == "dev"
Requires-Dist: myst-parser; extra == "dev"
Requires-Dist: pre-commit; extra == "dev"
Requires-Dist: toml; extra == "dev"
Requires-Dist: build; extra == "dev"
